eldonationtracker/__init__.py
eldonationtracker/cli.py
eldonationtracker/gui.py
eldonationtracker/icon.png
eldonationtracker/api/__init__.py
eldonationtracker/api/badge.py
eldonationtracker/api/donation.py
eldonationtracker/api/donor.py
eldonationtracker/api/participant.py
eldonationtracker/api/team.py
eldonationtracker/api/team_participant.py
eldonationtracker/tests/__init__.py
eldonationtracker/tests/test_badge.py
eldonationtracker/tests/test_donation.py
eldonationtracker/tests/test_donor.py
eldonationtracker/tests/test_participant.py
eldonationtracker/tests/test_team.py
eldonationtracker/tests/test_team_participant.py
eldonationtracker/ui/__init__.py
eldonationtracker/ui/about.py
eldonationtracker/ui/call_about.py
eldonationtracker/ui/call_logs.py
eldonationtracker/ui/call_main_gui.py
eldonationtracker/ui/call_settings.py
eldonationtracker/ui/call_tracker.py
eldonationtracker/ui/logs.py
eldonationtracker/ui/main_gui.py
eldonationtracker/ui/settings.py
eldonationtracker/ui/tracker.py
eldonationtracker/utils/__init__.py
eldonationtracker/utils/extralife_io.py
eldonationtracker/utils/update_available.py
eldonationtracker/utils/tests/__init__.py
eldonationtracker/utils/tests/test_extralife_io.py
eldonationtracker/utils/tests/test_update_available.py
eldonationtracker-8.0.0.dist-info/LICENSE
eldonationtracker-8.0.0.dist-info/METADATA
eldonationtracker-8.0.0.dist-info/WHEEL
eldonationtracker-8.0.0.dist-info/top_level.txt
eldonationtracker-8.0.0.dist-info/RECORD
