Metadata-Version: 2.1
Name: eldonationtracker
Version: 8.0.0
Summary: A Python-based donation tracker for Extra Life streams
Home-page: http://djotaku.github.io/ELDonationTracker/
Author: Eric Mesa
Author-email: eric@ericmesa.com
License: GPLv3
Keywords: extra life,XSplit,obs,livestreaming,video games
Classifier: Intended Audience :: End Users/Desktop
Classifier: License :: OSI Approved :: GNU General Public License v3 (GPLv3)
Classifier: Programming Language :: Python :: 3
License-File: LICENSE
Requires-Dist: xdgenvpy ==2.3.5
Requires-Dist: pyqt6 ==6.6.1
Requires-Dist: semver ==3.0.2
Requires-Dist: requests ==2.28.1
Requires-Dist: rich ==12.6.0
Requires-Dist: donordrivepython ==1.6.0
